RRtoolbox/__init__.py
RRtoolbox/core.py
RRtoolbox/run.py
RRtoolbox/shell.py
RRtoolbox/cv2_mock/Error.py
RRtoolbox/cv2_mock/__init__.py
RRtoolbox/cv2_mock/aruco.py
RRtoolbox/cv2_mock/bgsegm.py
RRtoolbox/cv2_mock/bioinspired.py
RRtoolbox/cv2_mock/cuda.py
RRtoolbox/cv2_mock/datasets.py
RRtoolbox/cv2_mock/detail.py
RRtoolbox/cv2_mock/dnn.py
RRtoolbox/cv2_mock/face.py
RRtoolbox/cv2_mock/fisheye.py
RRtoolbox/cv2_mock/flann.py
RRtoolbox/cv2_mock/freetype.py
RRtoolbox/cv2_mock/ft.py
RRtoolbox/cv2_mock/hdf.py
RRtoolbox/cv2_mock/instr.py
RRtoolbox/cv2_mock/line_descriptor.py
RRtoolbox/cv2_mock/ml.py
RRtoolbox/cv2_mock/motempl.py
RRtoolbox/cv2_mock/multicalib.py
RRtoolbox/cv2_mock/ocl.py
RRtoolbox/cv2_mock/ogl.py
RRtoolbox/cv2_mock/omnidir.py
RRtoolbox/cv2_mock/optflow.py
RRtoolbox/cv2_mock/plot.py
RRtoolbox/cv2_mock/ppf_match_3d.py
RRtoolbox/cv2_mock/rgbd.py
RRtoolbox/cv2_mock/saliency.py
RRtoolbox/cv2_mock/structured_light.py
RRtoolbox/cv2_mock/text.py
RRtoolbox/cv2_mock/videostab.py
RRtoolbox/cv2_mock/xfeatures2d.py
RRtoolbox/cv2_mock/xphoto.py
RRtoolbox/cv2_mock/ximgproc/__init__.py
RRtoolbox/cv2_mock/ximgproc/segmentation.py
RRtoolbox/lib/__init__.py
RRtoolbox/lib/cache.py
RRtoolbox/lib/config.py
RRtoolbox/lib/descriptors.py
RRtoolbox/lib/directory.py
RRtoolbox/lib/image.py
RRtoolbox/lib/inspector.py
RRtoolbox/lib/plotter.py
RRtoolbox/lib/root.py
RRtoolbox/lib/serverServices.py
RRtoolbox/lib/session.py
RRtoolbox/lib/arrayops/__init__.py
RRtoolbox/lib/arrayops/basic.py
RRtoolbox/lib/arrayops/convert.py
RRtoolbox/lib/arrayops/filters.py
RRtoolbox/lib/arrayops/mask.py
RRtoolbox/tools/__init__.py
RRtoolbox/tools/lens.py
RRtoolbox/tools/segmentation.py
RRtoolbox/tools/selectors.py
RRtoolbox/tools/sticher.py
rrtools-1.1.0a1.post1.dist-info/DESCRIPTION.rst
rrtools-1.1.0a1.post1.dist-info/METADATA
rrtools-1.1.0a1.post1.dist-info/RECORD
rrtools-1.1.0a1.post1.dist-info/WHEEL
rrtools-1.1.0a1.post1.dist-info/entry_points.txt
rrtools-1.1.0a1.post1.dist-info/metadata.json
rrtools-1.1.0a1.post1.dist-info/top_level.txt
