Metadata-Version: 2.0
Name: rrtools
Version: 1.1.0a1.post1
Summary: Raster Restoration tools
Home-page: https://github.com/davtoh/RRtools
Author: David Toro
Author-email: davsamirtor@gmail.com
License: BSD
Keywords: sample setuptools development
Platform: any
Classifier: Development Status :: 3 - Alpha
Classifier: Intended Audience :: Developers
Classifier: Intended Audience :: Education
Classifier: Intended Audience :: Science/Research
Classifier: Intended Audience :: End Users/Desktop
Classifier: License :: OSI Approved :: BSD License
Classifier: Natural Language :: English
Classifier: Operating System :: POSIX :: Linux
Classifier: Operating System :: Microsoft :: Windows
Classifier: Programming Language :: Python
Classifier: Programming Language :: Python :: 2
Classifier: Programming Language :: Python :: 2.7
Classifier: Programming Language :: Python :: 3
Classifier: Programming Language :: Python :: 3.2
Classifier: Programming Language :: Python :: 3.3
Classifier: Programming Language :: Python :: 3.4
Classifier: Programming Language :: Python :: 3.5
Classifier: Topic :: Education
Classifier: Topic :: Scientific/Engineering :: Artificial Intelligence
Classifier: Topic :: Software Development :: Libraries
Classifier: Topic :: Software Development :: Libraries :: Python Modules
Requires-Dist: appdirs (>=1.4)
Requires-Dist: dill (>=0.2)
Requires-Dist: future (>=0.16)
Requires-Dist: joblib (>=0.8)
Requires-Dist: matplotlib (>=1.4)
Requires-Dist: numpy (>=1.9)
Requires-Dist: packaging (>=16.8)
Requires-Dist: pycallgraph (>=1)
Requires-Dist: pyperclip (>=1.5)
Requires-Dist: pyqtgraph (>=0.9)
Requires-Dist: sympy (>=1)
